{
    "data": {
        "job": {
            "id": "a1081751",
            "statistic": {
                "onDomains": [
                    {
                        "id": "51"
                    },
                    {
                        "id": "46"
                    },
                    {
                        "id": "53"
                    },
                    {
                        "id": "35"
                    },
                    {
                        "id": "15"
                    },
                    {
                        "id": "49"
                    },
                    {
                        "id": "47"
                    },
                    {
                        "id": "13"
                    }
                ]
            }
        }
    }
}